wordjc/__init__.py
wordjc/pivot.py
wordjc/quot.py
wordjc/ta.py
wordjc/tm.py
wordjc/util.py
wordjc/viz.py
wordjc/data/Book Category.xlsx
wordjc/data/__init__.py
wordjc/data/bible_vocab.txt
wordjc/data/book_cat.csv
wordjc/data/book_categories.csv
wordjc/data/book_no.csv
wordjc/data/cuv.csv
wordjc/data/web.csv
wordjc/dictionary/__init__.py
wordjc/dictionary/dict.txt.big.txt
wordjc/dictionary/stopWord_cloud.txt
wordjc/dictionary/stopWord_cloudmod.txt
wordjc/dictionary/stopWord_summar.txt
wordjc/dictionary/stopWord_test.txt
wordjc/dictionary/stopWord_union.txt
wordjc/dictionary/user_dict_test.txt
wordjc/dictionary/userdict.txt
wordjc/images/__init__.py
wordjc/images/heart.jpg
wordjc-0.1.34.dist-info/METADATA
wordjc-0.1.34.dist-info/WHEEL
wordjc-0.1.34.dist-info/top_level.txt
wordjc-0.1.34.dist-info/RECORD
