Metadata-Version: 2.1
Name: wordjc
Version: 0.1.34
Summary: Scripture (Word) Visualization
Author: Johnny Cheng
Author-email: <drjohnnycheng@gmail.com>
License: UNKNOWN
Keywords: word,scripture,visualization
Platform: UNKNOWN
Classifier: Development Status :: 3 - Alpha
Classifier: Intended Audience :: Education
Classifier: Intended Audience :: Science/Research
Classifier: Intended Audience :: Religion
Classifier: Programming Language :: Python :: 3
Classifier: Operating System :: MacOS :: MacOS X
Classifier: Operating System :: Microsoft :: Windows
Requires-Dist: numpy
Requires-Dist: pandas
Requires-Dist: importlib-resources
Requires-Dist: regex
Requires-Dist: nltk
Requires-Dist: matplotlib
Requires-Dist: wordcloud
Requires-Dist: pillow
Requires-Dist: jieba
Requires-Dist: gensim
Requires-Dist: pyLDAvis
